{"P7": {"labels": ["adb\u547d\u4ee4"], "postTitle": "\u3010adb\u547d\u4ee4\u3011adb\u5e38\u7528\u547d\u4ee4", "postUrl": "post/%E3%80%90adb-ming-ling-%E3%80%91adb-chang-yong-ming-ling.html", "createdDate": "2024-08-14", "dateLabelColor": "#bc4c00"}, "P6": {"labels": ["Linux"], "postTitle": "\u3010Linux\u3011\u76f8\u5173\u6982\u5ff5\u4e0e\u64cd\u4f5c\u547d\u4ee4", "postUrl": "post/%E3%80%90Linux%E3%80%91-xiang-guan-gai-nian-yu-cao-zuo-ming-ling.html", "createdDate": "2024-07-29", "dateLabelColor": "#bc4c00"}, "P5": {"labels": ["\u8f6f\u4ef6\u6d4b\u8bd5", "\u6d4b\u8bd5\u57fa\u7840"], "postTitle": "\u3010\u6d4b\u8bd5\u57fa\u7840\u3011\u7f3a\u9677\u76f8\u5173\u6982\u5ff5", "postUrl": "post/%E3%80%90-ce-shi-ji-chu-%E3%80%91-que-xian-xiang-guan-gai-nian.html", "createdDate": "2024-07-15", "dateLabelColor": "#bc4c00"}, "P4": {"labels": ["\u8f6f\u4ef6\u6d4b\u8bd5", "\u6d4b\u8bd5\u57fa\u7840"], "postTitle": "\u3010\u6d4b\u8bd5\u57fa\u7840\u3011\u7528\u4f8b\u8bbe\u8ba1\u65b9\u6cd5\uff08\u9519\u8bef\u63a8\u8350\u6cd5\u3001\u5192\u70df\uff09", "postUrl": "post/%E3%80%90-ce-shi-ji-chu-%E3%80%91-yong-li-she-ji-fang-fa-%EF%BC%88-cuo-wu-tui-jian-fa-%E3%80%81-mao-yan-%EF%BC%89.html", "createdDate": "2024-07-10", "dateLabelColor": "#bc4c00"}, "P3": {"labels": ["\u8f6f\u4ef6\u6d4b\u8bd5", "\u6d4b\u8bd5\u57fa\u7840"], "postTitle": "\u3010\u6d4b\u8bd5\u57fa\u7840\u3011\u7528\u4f8b\u8bbe\u8ba1\u65b9\u6cd5\uff08\u5224\u5b9a\u8868\u3001\u573a\u666f\u6cd5\uff09", "postUrl": "post/%E3%80%90-ce-shi-ji-chu-%E3%80%91-yong-li-she-ji-fang-fa-%EF%BC%88-pan-ding-biao-%E3%80%81-chang-jing-fa-%EF%BC%89.html", "createdDate": "2024-07-09", "dateLabelColor": "#bc4c00"}, "P2": {"labels": ["\u8f6f\u4ef6\u6d4b\u8bd5", "\u6d4b\u8bd5\u57fa\u7840"], "postTitle": "\u3010\u6d4b\u8bd5\u57fa\u7840\u3011\u7528\u4f8b\u8bbe\u8ba1\u65b9\u6cd5\uff08\u7b49\u4ef7\u7c7b\u3001\u8fb9\u754c\u503c\uff09", "postUrl": "post/%E3%80%90-ce-shi-ji-chu-%E3%80%91-yong-li-she-ji-fang-fa-%EF%BC%88-deng-jia-lei-%E3%80%81-bian-jie-zhi-%EF%BC%89.html", "createdDate": "2024-07-05", "dateLabelColor": "#bc4c00"}, "P1": {"labels": ["\u8f6f\u4ef6\u6d4b\u8bd5", "\u6d4b\u8bd5\u57fa\u7840"], "postTitle": "\u3010\u6d4b\u8bd5\u57fa\u7840\u3011\u8f6f\u4ef6\u6d4b\u8bd5\u76f8\u5173\u6982\u5ff5", "postUrl": "post/%E3%80%90-ce-shi-ji-chu-%E3%80%91-ruan-jian-ce-shi-xiang-guan-gai-nian.html", "createdDate": "2024-07-05", "dateLabelColor": "#bc4c00"}, "labelColorDict": {"adb\u547d\u4ee4": "#d876e3", "duplicate": "#cfd3d7", "enhancement": "#a2eeef", "good first issue": "#7057ff", "help wanted": "#008672", "invalid": "#e4e669", "Linux": "#90AEF3", "wontfix": "#ffffff", "\u6d4b\u8bd5\u57fa\u7840": "#0EAD63", "\u8f6f\u4ef6\u6d4b\u8bd5": "#d73a4a"}}